pytest_netconf/__init__.py
pytest_netconf/constants.py
pytest_netconf/exceptions.py
pytest_netconf/netconfserver.py
pytest_netconf/pytest_plugin.py
pytest_netconf/settings.py
pytest_netconf/sshserver.py
pytest_netconf/version.py
pytest_netconf-0.2.0.dist-info/METADATA
pytest_netconf-0.2.0.dist-info/WHEEL
pytest_netconf-0.2.0.dist-info/entry_points.txt
pytest_netconf-0.2.0.dist-info/licenses/LICENSE
pytest_netconf-0.2.0.dist-info/RECORD
