Metadata-Version: 2.4
Name: pytest-netconf
Version: 0.2.0
Summary: A pytest plugin that provides a mock NETCONF (RFC6241/RFC6242) server for local testing.
License: Apache-2.0
License-File: LICENSE
Keywords: Netconf,Network automation,Network engineering,Network testing
Author: Adam Kirchberger
Author-email: adam.kirchberger@nomios.co.uk
Requires-Python: >=3.8,<4.0
Classifier: Framework :: Pytest
Classifier: Intended Audience :: Developers
Classifier: Intended Audience :: Telecommunications Industry
Classifier: License :: OSI Approved :: Apache Software License
Classifier: Programming Language :: Python :: 3
Classifier: Programming Language :: Python :: 3.8
Classifier: Programming Language :: Python :: 3.9
Classifier: Programming Language :: Python :: 3.10
Classifier: Programming Language :: Python :: 3.11
Classifier: Programming Language :: Python :: 3.12
Classifier: Programming Language :: Python :: 3.13
Classifier: Programming Language :: Python :: 3.14
Classifier: Topic :: Software Development :: Testing
Classifier: Topic :: Software Development :: Testing :: Mocking
Classifier: Topic :: System :: Networking
Requires-Dist: paramiko (>=3.4.0,<4.0.0)
